linalgplus/Core.py
linalgplus/Distance.py
linalgplus/Factorization.py
linalgplus/Norms.py
linalgplus/Operations.py
linalgplus/Properties.py
linalgplus/__init__.py
linalgplus-0.1.2.dist-info/METADATA
linalgplus-0.1.2.dist-info/WHEEL
linalgplus-0.1.2.dist-info/top_level.txt
linalgplus-0.1.2.dist-info/RECORD
