Metadata-Version: 2.1
Name: linalgplus
Version: 0.1.2
Summary: A lightweight linear algebra library for Python
Home-page: https://github.com/yourusername/linalgplus
Author: Your Name
Author-email: you@example.com
Classifier: Programming Language :: Python :: 3
Classifier: License :: OSI Approved :: MIT License
Classifier: Operating System :: OS Independent
Requires-Python: >=3.7
